aa_psycopg/__init__.py
aa_psycopg/config.py
aa_psycopg/connection.py
aa_psycopg/pool.py
aa_psycopg/utils.py
aa_psycopg-0.1.10.dist-info/licenses/LICENSE.txt
aa_psycopg-0.1.10.dist-info/METADATA
aa_psycopg-0.1.10.dist-info/WHEEL
aa_psycopg-0.1.10.dist-info/top_level.txt
aa_psycopg-0.1.10.dist-info/RECORD
