Metadata-Version: 2.4
Name: aa_psycopg
Version: 0.1.10
Summary: Internal Partenamut library for PostgreSQL access using Psycopg 3
Author-email: Botquin Thomas <thomas.botquin@partenamut.com>
License: MIT License
Requires-Python: >=3.11
License-File: LICENSE.txt
Requires-Dist: psycopg[binary,pool]>=3.2.9
Requires-Dist: PyYAML>=6.0
Provides-Extra: pydantic
Requires-Dist: pydantic>=2.0; extra == "pydantic"
Provides-Extra: dev
Requires-Dist: ruff>=0.9.10; extra == "dev"
Requires-Dist: pre-commit>=4.1.0; extra == "dev"
Requires-Dist: ipywidgets>=8.1.5; extra == "dev"
Requires-Dist: ipykernel>=6.29.0; extra == "dev"
Dynamic: license-file
